[
    {
        "name": "ABBA",
        "slug": "abba",
        "config": {
            "points": 10,
            "players": {
                "min": -1,
                "max": -1
            },
            "equipment": [
                "PAPER",
                "PEN"
            ],
            "rules": [
                "Le jeu consiste à transformer une suite de lettres en appliquant des règles précises de réduction. À chaque tour, les joueurs modifient la chaîne en suivant ces règles jusqu'à ce qu’aucune autre transformation ne soit possible.",
                "Le but est d'obtenir la séquence la plus courte possible, et celui qui y parvient gagne la partie."
            ]
        },
        "challenges": [],
        "play": {
            "questions": {
                "set": false
            },
            "timer": {
                "set": false
            },
            "stopwatch": {
                "set": false
            },
            "words": {
                "set": false
            },
            "operations": {
                "set": false
            },
            "abba": {
                "set": true
            },
            "empty": {
                "set": false
            }
        }
    },
    {
        "name": "Attention tension",
        "slug": "attention-tension",
        "config": {
            "points": 30,
            "players": {
                "min": 2,
                "max": -1
            },
            "equipment": [],
            "rules": [
                "bli"
            ]
        },
        "challenges": [
            {
                "points": 10,
                "challenge": "Avec un crayon dans la bouche"
            },
            {
                "points": 20,
                "challenge": "En fermant les yeux"
            }
        ],
        "play": {
            "questions": {
                "set": true
            },
            "timer": {
                "set": true,
                "duration": 30000
            },
            "stopwatch": {
                "set": false
            },
            "words": {
                "set": false
            },
            "operations": {
                "set": false
            },
            "abba": {
                "set": false
            },
            "empty": {
                "set": false
            }
        }
    },
    {
        "name": "Bataille de pouces",
        "slug": "pouces",
        "config": {
            "points": 10,
            "players": {
                "min": 2,
                "max": -1
            },
            "equipment": [],
            "rules": [
                "poulalaaa",
                "pumpa",
                "lorem ipsum"
            ]
        },
        "challenges": [],
        "play": {
            "questions": {
                "set": false
            },
            "timer": {
                "set": false
            },
            "stopwatch": {
                "set": false
            },
            "words": {
                "set": false
            },
            "operations": {
                "set": false
            },
            "abba": {
                "set": false
            },
            "empty": {
                "set": true
            }
        }
    }
]